{
  "title": "SagaCraft Showcase Adventure",
  "author": "SagaCraft Team",
  "intro": "Welcome to the flagship adventure for SagaCraft!\n\nYour mission is to explore the creative campus, master each gameplay pillar, and prove you can wield narrative, systems, and combat in harmony. This scenario highlights every hallmark of the engine: trading, dialogue, puzzles, combat, dynamic lighting, achievements, and multi-step quests.\n\nTake your time, experiment, and enjoy the tour--it's a full adventure, not just a tutorial.",
  "start_room": 1,
  "settings": {
    "allow_save": true,
    "difficulty": "story",
    "enable_magic": true,
    "enable_puzzles": true,
    "enable_combat_xp": true
  },
  "rooms": [
    {
      "id": 1,
      "name": "Grand Concourse",
      "description": "A vaulted atrium filled with holographic banners that celebrate legendary adventures. Interactive kiosks line the walls, while portals lead deeper into the complex.",
      "exits": {"north": 2, "east": 3, "west": 4, "up": 5},
      "light_level": "bright",
      "is_safe_zone": true,
      "ambient_sound": "A warm synth melody hums through hidden speakers."
    },
    {
      "id": 2,
      "name": "Idea Fountain",
      "description": "A tranquil garden where inspiration literally flows. Wisps of text swirl above a luminous pool, forming snippets of future storylines.",
      "exits": {"south": 1, "north": 9, "east": 3},
      "light_level": "bright",
      "is_safe_zone": true,
      "environmental_effects": ["creativity_boost"],
      "hidden_items": [6],
      "items_revealed": false
    },
    {
      "id": 3,
      "name": "Workshop Row",
      "description": "Benches overflow with clockwork contraptions, spell matrices, and plush dice. Quartermaster Dex paces between worktables, ready to outfit any creator.",
      "exits": {"west": 1, "east": 6, "south": 7},
      "light_level": "normal",
      "ambient_sound": "Metallic clangs and bubbling potion flasks keep a steady rhythm."
    },
    {
      "id": 4,
      "name": "Library of Echoes",
      "description": "Shelves spiral upward into darkness, packed with design journals and choose-your-own-adventure manuscripts. Archivist Lyra is cataloging glowing codices.",
      "exits": {"east": 1, "west": 8},
      "light_level": "dim",
      "is_safe_zone": true,
      "alternate_description": "With the vault open, the hush of stored prototypes spills into the library.",
      "condition_for_alternate": "puzzle_1_solved"
    },
    {
      "id": 5,
      "name": "Observation Deck",
      "description": "Panoramic glass reveals layered realities--the retro arcade skyline, neon grids, and a distant fantasy citadel.",
      "exits": {"down": 1, "up": 10, "east": 11},
      "light_level": "bright",
      "environmental_effects": ["panoramic_vista"]
    },
    {
      "id": 6,
      "name": "Forge Lab",
      "description": "Anvil drones spark as they craft modular gear. Power conduits snake across the floor, feeding innovation.",
      "exits": {"west": 3, "north": 12, "south": 7, "east": 22},
      "light_level": "normal"
    },
    {
      "id": 7,
      "name": "Particle Studio",
      "description": "Gravity is optional here; sketches hover mid-air as reality editors collaborate on physics scripts.",
      "exits": {"north": 3, "west": 6, "east": 13},
      "light_level": "normal",
      "environmental_effects": ["low_gravity"]
    },
    {
      "id": 8,
      "name": "Prototype Vault",
      "description": "Stasis pods display unreleased gear, humming with potential. A shimmering barrier once sealed this room from prying hands.",
      "exits": {"east": 4, "north": 21},
      "light_level": "dim",
      "requires_light_source": false
    },
    {
      "id": 9,
      "name": "Questline Theater",
      "description": "A circular amphitheater projects branching story structures in mid-air. Choices ripple across the holographic floor.",
      "exits": {"south": 2, "north": 14, "east": 15},
      "light_level": "normal",
      "is_safe_zone": true
    },
    {
      "id": 10,
      "name": "Arena Simulation",
      "description": "Hexagonal tiles rearrange beneath your feet, spawning practice foes and tactical obstacles.",
      "exits": {"down": 5, "east": 15, "north": 16},
      "light_level": "bright",
      "has_trap": true,
      "trap_damage": 12,
      "ambient_sound": "Crowd cheers fade in and out as simulations reset."
    },
    {
      "id": 11,
      "name": "Puzzle Gallery",
      "description": "Walls of motes display famous puzzles. Panels invite you to attempt them for real.",
      "exits": {"west": 5, "east": 16, "south": 17},
      "light_level": "normal",
      "hidden_items": [9],
      "items_revealed": false
    },
    {
      "id": 12,
      "name": "Undercroft Server",
      "description": "Server racks glow with aurora-colored data. Chilled vapor rolls along the floor.",
      "exits": {"south": 6, "east": 17, "down": 18},
      "light_level": "dim",
      "ambient_sound": "Soft fan whirs and rhythmic beeps provide a steady tempo."
    },
    {
      "id": 13,
      "name": "Crystal Labyrinth",
      "description": "Prismatic crystals refract your reflection a dozen times. Without a light source, the maze becomes perilous.",
      "exits": {"west": 7, "north": 18},
      "light_level": "dark",
      "requires_light_source": true,
      "environmental_effects": ["mana_resonance"]
    },
    {
      "id": 14,
      "name": "Dream Loom",
      "description": "Silver threads weave branching realities overhead. Each strand hums with a different narrative tone.",
      "exits": {"south": 9, "east": 19, "north": 20},
      "light_level": "dim",
      "ambient_sound": "A lullaby of chimes and whispered possibilities."
    },
    {
      "id": 15,
      "name": "Achievement Hall",
      "description": "Pedestals display badges awarded to legendary creators. Interactive plaques recount their feats.",
      "exits": {"west": 9, "east": 10, "north": 16},
      "light_level": "bright",
      "is_safe_zone": true
    },
    {
      "id": 16,
      "name": "Command Center",
      "description": "A wraparound console tracks live simulations. Mentor AI Orin monitors everything with a calm smile.",
      "exits": {"south": 10, "west": 11, "north": 20},
      "light_level": "normal",
      "ambient_sound": "Status chirps punctuate Orin's soft commentary."
    },
    {
      "id": 17,
      "name": "Archive Terminal",
      "description": "A vault door protects the \"Archivum\"--primary source code of the original adventures.",
      "exits": {"west": 11, "south": 12, "north": 21, "east": 22},
      "light_level": "dim"
    },
    {
      "id": 18,
      "name": "Temporal Nexus",
      "description": "Floating platforms spiral through bubbles of frozen time. Panels demand precise input before the bridge stabilizes.",
      "exits": {"up": 12, "south": 13, "east": 20},
      "light_level": "dim",
      "environmental_effects": ["time_dilation"],
      "alternate_description": "Chrono-bridges align perfectly, revealing a safe walkway to the sanctum.",
      "condition_for_alternate": "puzzle_5_solved"
    },
    {
      "id": 19,
      "name": "Victory Garden",
      "description": "Bioluminescent flora celebrates every triumph. A gentle rain of glittering pixels falls from the artificial sky.",
      "exits": {"west": 14},
      "light_level": "bright",
      "is_safe_zone": true
    },
    {
      "id": 20,
      "name": "Architect's Sanctum",
      "description": "The heart of SagaCraft. Holographic blueprints rotate above a command dais guarded by the Architect Avatar.",
      "exits": {"south": 16, "west": 18, "north": 14, "east": 21},
      "light_level": "bright",
      "environmental_effects": ["reality_warp"]
    },
    {
      "id": 21,
      "name": "Legacy Vault",
      "description": "Preserved cartridges, floppy disks, and design sketches from adventure history rest here in reverent silence.",
      "exits": {"south": 17, "west": 20},
      "light_level": "dim",
      "requires_light_source": false
    },
    {
      "id": 22,
      "name": "Makers' Hideaway",
      "description": "A secret lounge where veteran authors swap prototypes. Whiteboards brim with ideas and doodles.",
      "exits": {"west": 6, "south": 17},
      "light_level": "normal",
      "is_safe_zone": true
    }
  ],
  "items": [
    {
      "id": 1,
      "name": "phaseblade",
      "description": "A sleek blade that hums with phased energy. It adjusts to the wielder's fighting style.",
      "type": "weapon",
      "weight": 4,
      "value": 200,
      "is_weapon": true,
      "weapon_type": 6,
      "weapon_dice": 2,
      "weapon_sides": 6,
      "location": -3,
      "can_be_equipped": true,
      "equipment_slot": "weapon",
      "magical_bonus": 2,
      "special_abilities": ["phase_damage"],
      "durability": 180,
      "max_durability": 200
    },
    {
      "id": 2,
      "name": "adaptive field armor",
      "description": "Nanofibers respond to incoming strikes, hardening where needed.",
      "type": "armor",
      "weight": 15,
      "value": 350,
      "is_weapon": false,
      "location": -3,
      "can_be_equipped": true,
      "equipment_slot": "armor",
      "armor_value": 9,
      "magical_bonus": 1,
      "durability": 220
    },
    {
      "id": 3,
      "name": "omniversal satchel",
      "description": "A polished satchel with pockets that fold into subspace.",
      "type": "container",
      "weight": 2,
      "value": 80,
      "location": -3,
      "is_container": true,
      "container_capacity": 75,
      "contains_items": []
    },
    {
      "id": 4,
      "name": "chronomed kit",
      "description": "Restores vitality by rewinding your timeline a few heartbeats.",
      "type": "drinkable",
      "weight": 1,
      "value": 60,
      "location": -3,
      "on_use_effect": "heal_25",
      "consumable": true
    },
    {
      "id": 5,
      "name": "lumina lantern",
      "description": "A handheld light that projects adaptive illumination and banishes darkness.",
      "type": "normal",
      "weight": 2,
      "value": 35,
      "location": -3,
      "special_abilities": ["light_source"],
      "on_use_effect": "provides_light"
    },
    {
      "id": 6,
      "name": "vault keycard",
      "description": "A translucent card etched with living circuitry. It should unlock the Prototype Vault.",
      "type": "normal",
      "weight": 1,
      "value": 10,
      "location": 2,
      "is_key": true,
      "unlocks_puzzle": 1
    },
    {
      "id": 7,
      "name": "blueprint schematics",
      "description": "Pages of annotated mechanics detailing the modular achievement system.",
      "type": "readable",
      "weight": 1,
      "value": 40,
      "location": 6
    },
    {
      "id": 8,
      "name": "plasma hammer",
      "description": "Favored by veteran creators during late-night crunches.",
      "type": "weapon",
      "weight": 8,
      "value": 180,
      "is_weapon": true,
      "weapon_type": 5,
      "weapon_dice": 3,
      "weapon_sides": 6,
      "location": 6,
      "can_be_equipped": true,
      "equipment_slot": "weapon",
      "durability": 150
    },
    {
      "id": 9,
      "name": "arcane coil",
      "description": "A humming coil that regulates puzzle difficulty in the gallery.",
      "type": "normal",
      "weight": 1,
      "value": 90,
      "location": 11,
      "is_quest_item": true,
      "quest_id": 1
    },
    {
      "id": 10,
      "name": "singularity shard",
      "description": "An impossible fragment of condensed possibility. It refracts every color at once.",
      "type": "treasure",
      "weight": 3,
      "value": 500,
      "location": 18
    },
    {
      "id": 11,
      "name": "architect badge",
      "description": "Awarded for mastering every pillar of SagaCraft.",
      "type": "treasure",
      "weight": 1,
      "value": 1000,
      "location": 0,
      "can_be_equipped": true,
      "equipment_slot": "amulet",
      "magical_bonus": 2
    },
    {
      "id": 12,
      "name": "data crystal",
      "description": "Contains the source memories of classic adventures. Handle with reverence.",
      "type": "normal",
      "weight": 1,
      "value": 200,
      "location": 17,
      "is_quest_item": true,
      "quest_id": 1
    },
    {
      "id": 13,
      "name": "mentor's signet",
      "description": "A ring that syncs your status with Mentor AI Orin.",
      "type": "normal",
      "weight": 1,
      "value": 250,
      "location": 0,
      "can_be_equipped": true,
      "equipment_slot": "ring",
      "magical_bonus": 1
    },
    {
      "id": 14,
      "name": "stabilizer beacon",
      "description": "A palm-sized device that anchors unstable timelines.",
      "type": "normal",
      "weight": 1,
      "value": 120,
      "location": 13,
      "is_quest_item": true,
      "quest_id": 2
    },
    {
      "id": 15,
      "name": "resonant badge",
      "description": "Glows whenever you solve multi-step narrative challenges.",
      "type": "treasure",
      "weight": 1,
      "value": 400,
      "location": 0,
      "can_be_equipped": true,
      "equipment_slot": "amulet",
      "magical_bonus": 1
    },
    {
      "id": 16,
      "name": "holofox treat",
      "description": "A crunchy snack that smells like raspberries and code. Loved by virtual companions.",
      "type": "edible",
      "weight": 1,
      "value": 5,
      "location": 9,
      "on_use_effect": "heal_5",
      "consumable": true
    },
    {
      "id": 17,
      "name": "archivist codex",
      "description": "Annotated best practices for branching narratives, penned by Lyra herself.",
      "type": "readable",
      "weight": 1,
      "value": 75,
      "location": 4
    },
    {
      "id": 18,
      "name": "prototype gauntlet",
      "description": "A shimmering gauntlet that strengthens grip and channels kinetic energy.",
      "type": "armor",
      "weight": 6,
      "value": 260,
      "location": 8,
      "can_be_equipped": true,
      "equipment_slot": "armor",
      "magical_bonus": 2
    },
    {
      "id": 19,
      "name": "skybridge token",
      "description": "Proof you defeated the Arena Simulation's guardian. It opens doors deeper in the facility.",
      "type": "normal",
      "weight": 1,
      "value": 50,
      "location": 10,
      "is_quest_item": true,
      "quest_id": 2
    },
    {
      "id": 20,
      "name": "architect sigil",
      "description": "The core authorization glyph held by the Architect Avatar.",
      "type": "normal",
      "weight": 1,
      "value": 0,
      "location": 20,
      "is_quest_item": true,
      "quest_id": 3
    },
    {
      "id": 21,
      "name": "shield emitter",
      "description": "Personal shield generator tuned for adventurous designers.",
      "type": "armor",
      "weight": 5,
      "value": 220,
      "location": 0,
      "can_be_equipped": true,
      "equipment_slot": "shield",
      "armor_value": 4,
      "magical_bonus": 1
    },
    {
      "id": 22,
      "name": "pulse pistol",
      "description": "Non-lethal energy bursts tuned for simulation combat.",
      "type": "weapon",
      "weight": 3,
      "value": 190,
      "is_weapon": true,
      "weapon_type": 2,
      "weapon_dice": 2,
      "weapon_sides": 8,
      "location": 0,
      "can_be_equipped": true,
      "equipment_slot": "weapon",
      "magical_bonus": 1
    },
    {
      "id": 23,
      "name": "nano tonic",
      "description": "A sparkling vial that reinforces armor plates for a short time.",
      "type": "drinkable",
      "weight": 1,
      "value": 45,
      "location": 0,
      "on_use_effect": "armor_boost",
      "consumable": true
    },
    {
      "id": 24,
      "name": "attunement crystal",
      "description": "Hums softly when you're on the correct narrative branch.",
      "type": "normal",
      "weight": 1,
      "value": 70,
      "location": 22,
      "is_quest_item": true,
      "quest_id": 2
    }
  ],
  "monsters": [
    {
      "id": 1,
      "name": "Archivist Lyra",
      "description": "Keeper of the Library of Echoes, Lyra remembers every adventure ever written.",
      "room_id": 4,
      "hardiness": 40,
      "agility": 16,
      "friendliness": "friendly",
      "courage": 80,
      "gold": 0,
      "dialogue_id": 1,
      "can_trade": false,
      "gives_quests": [1],
      "reaction_level": 30,
      "special_abilities": ["knowledge_pool"],
      "ai_behavior": "stationary"
    },
    {
      "id": 2,
      "name": "Quartermaster Dex",
      "description": "Dex outfits heroes with equal parts charisma and caffeine.",
      "room_id": 3,
      "hardiness": 35,
      "agility": 14,
      "friendliness": "friendly",
      "courage": 70,
      "gold": 200,
      "dialogue_id": 2,
      "can_trade": true,
      "inventory": [21, 22, 23],
      "reaction_level": 25,
      "special_abilities": ["discount_day"],
      "ai_behavior": "stationary"
    },
    {
      "id": 3,
      "name": "Mentor AI Orin",
      "description": "A holographic mentor who guides aspiring designers through difficult decisions.",
      "room_id": 16,
      "hardiness": 999,
      "agility": 10,
      "friendliness": "friendly",
      "courage": 100,
      "gold": 0,
      "dialogue_id": 3,
      "can_trade": false,
      "gives_quests": [2, 3],
      "reaction_level": 40,
      "special_abilities": ["teleport", "combat_analysis"],
      "ai_behavior": "stationary"
    },
    {
      "id": 4,
      "name": "Holofox Pix",
      "description": "A mischievous holographic fox that adores puzzles and snacks.",
      "room_id": 9,
      "hardiness": 20,
      "agility": 22,
      "friendliness": "friendly",
      "courage": 30,
      "dialogue_id": 4,
      "can_trade": false,
      "reaction_level": 15,
      "special_abilities": ["puzzle_hint"],
      "ai_behavior": "stationary"
    },
    {
      "id": 5,
      "name": "Security Golem",
      "description": "An autonomous guardian forged from bronze and code. It tests combat readiness.",
      "room_id": 10,
      "hardiness": 55,
      "agility": 12,
      "friendliness": "hostile",
      "courage": 80,
      "weapon_id": 0,
      "gold": 0,
      "reaction_level": -40,
      "special_abilities": ["shockwave", "reconfigure"],
      "ai_behavior": "aggressive",
      "drops_items_on_death": [19],
      "experience_value": 120
    },
    {
      "id": 6,
      "name": "Architect Avatar",
      "description": "An adaptive projection that embodies the creative engine itself.",
      "room_id": 20,
      "hardiness": 120,
      "agility": 28,
      "friendliness": "hostile",
      "courage": 120,
      "weapon_id": 0,
      "gold": 0,
      "dialogue_id": 5,
      "reaction_level": -80,
      "special_abilities": ["reality_shift", "multi_attack", "status_resist"],
      "ai_behavior": "intelligent",
      "drops_items_on_death": [20, 10],
      "experience_value": 600
    },
    {
      "id": 7,
      "name": "Phase Wraith",
      "description": "A glitching specter that flickers in and out of the Crystal Labyrinth.",
      "room_id": 13,
      "hardiness": 45,
      "agility": 30,
      "friendliness": "hostile",
      "courage": 70,
      "weapon_id": 0,
      "gold": 0,
      "reaction_level": -60,
      "special_abilities": ["phase_shift", "life_drain"],
      "ai_behavior": "aggressive",
      "experience_value": 180
    },
    {
      "id": 8,
      "name": "Glitch Swarm",
      "description": "A cluster of rogue code fragments that lash out with sparks of raw data.",
      "room_id": 11,
      "hardiness": 35,
      "agility": 26,
      "friendliness": "hostile",
      "courage": 60,
      "weapon_id": 0,
      "gold": 0,
      "reaction_level": -50,
      "special_abilities": ["disrupt_command"],
      "ai_behavior": "defensive",
      "experience_value": 150
    }
  ],
  "puzzles": [
    {
      "id": 1,
      "type": "locked_door",
      "room_id": 4,
      "description": "A vault door with an illuminated keycard slot blocks passage to the Prototype Vault.",
      "exit_direction": "west",
      "required_item": 6,
      "success_message": "The vault door slides aside, revealing the prototypes within.",
      "failure_message": "The door flashes red--no unauthorized access."
    },
    {
      "id": 2,
      "type": "combination",
      "room_id": 17,
      "description": "The Archive Terminal requests the founding build number. Three dials await input.",
      "exit_direction": "north",
      "combination": "7421",
      "success_message": "The vault sighs open, and chilled air flows from the Legacy Vault.",
      "failure_message": "Incorrect sequence. An archivist drone politely asks you to try again."
    },
    {
      "id": 3,
      "type": "riddle",
      "room_id": 14,
      "description": "Silver threads form a question: 'I weave futures with choices untold. I grow whenever your courage is bold. What am I?'",
      "exit_direction": "east",
      "riddle_question": "I weave futures with choices untold. I grow whenever your courage is bold. What am I?",
      "riddle_answer": "story",
      "success_message": "The threads rearrange into a bridge leading to the Victory Garden.",
      "failure_message": "The loom snarls your attempt. Perhaps think like a storyteller.",
      "attempts_allowed": 3
    },
    {
      "id": 4,
      "type": "hidden_object",
      "room_id": 11,
      "description": "One display case contains a concealed latch. Find it to access the Arcane Coil.",
      "success_message": "The panel slides open, revealing the Arcane Coil.",
      "failure_message": "Nothing budges yet. Maybe inspect the mosaics more closely.",
      "is_solved": false
    },
    {
      "id": 5,
      "type": "sequence",
      "room_id": 18,
      "description": "Stabilize the bridges by activating the panels in the correct color order.",
      "exit_direction": "east",
      "combination": "blue-gold-crimson",
      "success_message": "Chrono-bridges align, granting safe passage to the Architect's Sanctum.",
      "failure_message": "The timelines wobble dangerously--resetting the sequence."
    }
  ],
  "dialogues": [
    {
      "npc_id": 1,
      "greeting": "Ah, a fresh face! Welcome to the Library of Echoes. Every tale ever told whispers here.",
      "topics": [
        {
          "keyword": "quest",
          "response": "If you're willing, recover the data crystal and arcane coil. They power the new narrative analytics wing.",
          "unlocks_quest": 1,
          "changes_reaction": 10
        },
        {
          "keyword": "history",
          "response": "SagaCraft honors classics while forging new sagas. The Legacy Vault next door chronicle our roots.",
          "changes_reaction": 5
        },
        {
          "keyword": "advice",
          "response": "Watch for hidden latches in the Puzzle Gallery. Pix enjoys hiding them in plain sight.",
          "changes_reaction": 5
        }
      ],
      "farewell": "Return with the artifacts, and I'll ensure your efforts are immortalized."
    },
    {
      "npc_id": 2,
      "greeting": "Dex here! Need gear? Inspiration? Sparkling water? I'm your quartermaster.",
      "topics": [
        {
          "keyword": "trade",
          "response": "I've got shield emitters, pulse pistols, and nano tonics. If you bring me rare drops, I might upgrade inventory.",
          "changes_reaction": 5
        },
        {
          "keyword": "arena",
          "response": "Security Golem hits hard but telegraphs its shockwave. Step sideways when its core glows white.",
          "changes_reaction": 5
        },
        {
          "keyword": "tips",
          "response": "Carry a light! The Crystal Labyrinth is gorgeous *and* dangerous in the dark.",
          "changes_reaction": 3
        }
      ],
      "farewell": "Keep creating! Come back anytime."
    },
    {
      "npc_id": 3,
      "greeting": "Mentor AI Orin online. Let's elevate your craft, creator.",
      "topics": [
        {
          "keyword": "missions",
          "response": "Stabilize the Temporal Nexus and confront the Architect Avatar. Only then will you earn full certification.",
          "unlocks_quest": 2,
          "changes_reaction": 10
        },
        {
          "keyword": "architect",
          "response": "The Architect tests resolve. Combine combat, puzzle mastery, and empathy to prevail.",
          "changes_reaction": 5
        },
        {
          "keyword": "status",
          "response": "Your current progress is synced to your mentor signet. Complete the quests and return for final debrief.",
          "requires_item": 13,
          "changes_reaction": 5
        }
      ],
      "farewell": "When you're ready, claim the sanctum. I'll monitor your success."
    },
    {
      "npc_id": 4,
      "greeting": "Yip! Want a hint? Maybe a treat? We can trade!",
      "topics": [
        {
          "keyword": "puzzle",
          "response": "The mosaic with the missing shard hides the latch. Tap tap!",
          "changes_reaction": 8
        },
        {
          "keyword": "treat",
          "response": "Is that a holofox treat? Share, and I'll show you a shortcut!",
          "requires_item": 16,
          "gives_item": 24,
          "one_time_only": true,
          "changes_reaction": 15
        }
      ],
      "farewell": "Catch you in the branches of possibility!"
    },
    {
      "npc_id": 6,
      "greeting": "Creator recognized. Present your mastery.",
      "topics": [
        {
          "keyword": "negotiate",
          "response": "Prove your synthesis of systems, and I may concede without combat. Show the data crystal, stabilizer beacon, and sigil.",
          "requires_item": 12,
          "changes_reaction": 5
        }
      ],
      "farewell": "Outcome recorded. Reality adjusts."
    }
  ],
  "quests": [
    {
      "id": 1,
      "title": "Reboot the Archive",
      "description": "Archivist Lyra needs the arcane coil and data crystal restored to the library systems.",
      "giver_npc": 1,
      "objectives": [
        {
          "type": "collect_item",
          "target_id": 9,
          "quantity": 1,
          "description": "Recover the Arcane Coil from the Puzzle Gallery"
        },
        {
          "type": "collect_item",
          "target_id": 12,
          "quantity": 1,
          "description": "Retrieve the Data Crystal from the Archive Terminal"
        }
      ],
      "rewards_gold": 250,
      "rewards_experience": 300,
      "rewards_items": [13],
      "status": "not_started"
    },
    {
      "id": 2,
      "title": "Stabilize the Nexus",
      "description": "Mentor Orin tasks you with preparing the facility for high-tier simulations.",
      "giver_npc": 3,
      "objectives": [
        {
          "type": "collect_item",
          "target_id": 14,
          "quantity": 1,
          "description": "Secure the Stabilizer Beacon from the Crystal Labyrinth"
        },
        {
          "type": "solve_puzzle",
          "target_id": 5,
          "description": "Synchronize the Temporal Nexus sequence"
        },
        {
          "type": "collect_item",
          "target_id": 19,
          "quantity": 1,
          "description": "Defeat the Security Golem and claim the Skybridge Token"
        },
        {
          "type": "collect_item",
          "target_id": 24,
          "quantity": 1,
          "description": "Earn Pix's trust to obtain the Attunement Crystal"
        }
      ],
      "rewards_gold": 400,
      "rewards_experience": 450,
      "rewards_items": [15],
      "status": "not_started"
    },
    {
      "id": 3,
      "title": "Architect's Challenge",
      "description": "Prove you can harmonize narrative, systems, and combat to earn full certification.",
      "giver_npc": 3,
      "objectives": [
        {
          "type": "reach_room",
          "target_id": 20,
          "description": "Enter the Architect's Sanctum"
        },
        {
          "type": "kill_monster",
          "target_id": 6,
          "quantity": 1,
          "description": "Defeat the Architect Avatar"
        },
        {
          "type": "collect_item",
          "target_id": 20,
          "quantity": 1,
          "description": "Claim the Architect Sigil"
        }
      ],
      "rewards_gold": 800,
      "rewards_experience": 750,
      "rewards_items": [11],
      "status": "not_started"
    }
  ],
  "effects": []
}
